rebrand/__init__.py
rebrand/__main__.py
rebrand/rebrand.py
rebrand-0.0.12.dist-info/METADATA
rebrand-0.0.12.dist-info/WHEEL
rebrand-0.0.12.dist-info/entry_points.txt
rebrand-0.0.12.dist-info/top_level.txt
rebrand-0.0.12.dist-info/RECORD
